freesasa.cp310-win_amd64.pyd
freesasa-2.2.1.data/headers/Makefile.am
freesasa-2.2.1.data/headers/cif.cc
freesasa-2.2.1.data/headers/cif.hh
freesasa-2.2.1.data/headers/classifier.c
freesasa-2.2.1.data/headers/classifier.h
freesasa-2.2.1.data/headers/classifier_naccess.c
freesasa-2.2.1.data/headers/classifier_oons.c
freesasa-2.2.1.data/headers/classifier_protor.c
freesasa-2.2.1.data/headers/coord.c
freesasa-2.2.1.data/headers/coord.h
freesasa-2.2.1.data/headers/example.c
freesasa-2.2.1.data/headers/freesasa.c
freesasa-2.2.1.data/headers/freesasa.h
freesasa-2.2.1.data/headers/freesasa_internal.h
freesasa-2.2.1.data/headers/json.c
freesasa-2.2.1.data/headers/lexer.c
freesasa-2.2.1.data/headers/lexer.h
freesasa-2.2.1.data/headers/lexer.l
freesasa-2.2.1.data/headers/log.c
freesasa-2.2.1.data/headers/main.cc
freesasa-2.2.1.data/headers/nb.c
freesasa-2.2.1.data/headers/nb.h
freesasa-2.2.1.data/headers/node.c
freesasa-2.2.1.data/headers/parser.c
freesasa-2.2.1.data/headers/parser.h
freesasa-2.2.1.data/headers/parser.y
freesasa-2.2.1.data/headers/pdb.c
freesasa-2.2.1.data/headers/pdb.h
freesasa-2.2.1.data/headers/rsa.c
freesasa-2.2.1.data/headers/sasa_lr.c
freesasa-2.2.1.data/headers/sasa_sr.c
freesasa-2.2.1.data/headers/selection.c
freesasa-2.2.1.data/headers/selection.h
freesasa-2.2.1.data/headers/structure.c
freesasa-2.2.1.data/headers/util.c
freesasa-2.2.1.data/headers/xml.c
freesasa-2.2.1.dist-info/LICENSE.txt
freesasa-2.2.1.dist-info/METADATA
freesasa-2.2.1.dist-info/WHEEL
freesasa-2.2.1.dist-info/top_level.txt
freesasa-2.2.1.dist-info/RECORD
